SandsPythonFunctions/EmailFunctions.py
SandsPythonFunctions/FormatFunctions.py
SandsPythonFunctions/MultiprocessingFunctions.py
SandsPythonFunctions/PandasFunctions.py
SandsPythonFunctions/ParquetFunctions.py
SandsPythonFunctions/TextFunctions.py
SandsPythonFunctions/TimerFunctions.py
SandsPythonFunctions/__init__.py
sandspythonfunctions-0.1.0.dist-info/LICENSE
sandspythonfunctions-0.1.0.dist-info/WHEEL
sandspythonfunctions-0.1.0.dist-info/METADATA
sandspythonfunctions-0.1.0.dist-info/RECORD
