Metadata-Version: 2.1
Name: sandspythonfunctions
Version: 0.1.0
Summary: Functions I use regularly with my python projects
Home-page: https://github.com/ldsands/SandsPythonFunctions
License: MIT
Author: ldsands
Author-email: ldsands@outlook.com
Requires-Python: >=3.9,<3.11
Classifier: License :: OSI Approved :: MIT License
Classifier: Programming Language :: Python :: 3
Classifier: Programming Language :: Python :: 3.9
Requires-Dist: black (>=20.8b1,<21.0)
Requires-Dist: flake8 (>=3.8.4,<4.0.0)
Requires-Dist: isort (>=5.7.0,<6.0.0)
Requires-Dist: numpy (>=1.21.2,<2.0.0)
Requires-Dist: openpyxl (>=3.0.7,<4.0.0)
Requires-Dist: pandas (>=1.3.3,<2.0.0)
Requires-Dist: pretty-errors (>=1.2.24,<2.0.0)
Requires-Dist: pyarrow (>=5.0.0,<6.0.0)
Requires-Dist: vaex (>=4.5.0,<5.0.0)
Requires-Dist: wheel (>=0.37.0,<0.38.0)
Requires-Dist: zstandard (>=0.15.1,<0.16.0)
Project-URL: Repository, https://github.com/ldsands/SandsPythonFunctions
